.gitignore
MANIFEST.in
README.md
README.rst
setup.cfg
setup.py
dist/minidetector2-0.0.2/minidetector2/search_strings.txt
minidetector2/__init__.py
minidetector2/search_strings.txt
minidetector2/useragents.py
minidetector2.egg-info/PKG-INFO
minidetector2.egg-info/SOURCES.txt
minidetector2.egg-info/dependency_links.txt
minidetector2.egg-info/top_level.txt
minidetector2/tests/__init__.py